README.rst
setup.py
mvoauthapi/__init__.py
mvoauthapi/client.py
mvoauthapi/errors.py
mvoauthapi/utils.py
mvoauthapi.egg-info/PKG-INFO
mvoauthapi.egg-info/SOURCES.txt
mvoauthapi.egg-info/dependency_links.txt
mvoauthapi.egg-info/requires.txt
mvoauthapi.egg-info/top_level.txt