Metadata-Version: 1.1
Name: mvoauthapi
Version: 0.2
Summary: Mobile Vikings OAuth API Client
Home-page: http://github.com/kvsn/mvoauthapi
Author: Koen Vossen
Author-email: koen.vossen@citylive.be
License: BSD
Keywords: mobile vikings oauth api client
Platform: UNKNOWN
Classifier: Intended Audience :: Developers
Classifier: Programming Language :: Python
Classifier: Operating System :: OS Independent
